Metadata-Version: 1.1
Name: dagmawi-time
Version: 0.1
Summary: Create/modify an instance of time
Home-page: UNKNOWN
Author: Dagmawi Mulugeta
Author-email: djdg432@gmail.com
License: None
Platform: UNKNOWN
Classifier: Programming Language :: Python :: 2.7
Classifier: Intended Audience :: Science/Research
Classifier: Natural Language :: English
Classifier: Operating System :: MacOS
Classifier: Topic :: Software Development :: Libraries :: Python Modules
